{
	"id": "47c058a3-54d3-42b1-88df-3b420fa1ede2",
	"name": "Orkes Conductor API Environment",
	"values": [
		{
			"key": "baseURL",
			"value": "https://developer.orkescloud.com",
			"type": "default",
			"enabled": true
		},
		{
			"key": "KEY",
			"value": "16qp64eb38d9-7e71-11f0-b60b-c227118a1889",
			"type": "secret",
			"enabled": true
		},
		{
			"key": "SECRET",
			"value": "vvLG0hYcNx89ev6xKZRzXjfvR8E7reWJUl5bSCBvZuq2XvEP",
			"type": "secret",
			"enabled": true
		},
		{
			"key": "orkes_jwt",
			"value": "",
			"type": "any",
			"enabled": true
		},
		{
			"key": "workflowId",
			"value": "",
			"type": "any",
			"enabled": true
		},
		{
			"key": "contact_email",
			"value": "",
			"type": "default",
			"description": {
				"content": "",
				"type": "text/plain"
			},
			"enabled": true
		},
		{
			"key": "business_name",
			"value": "",
			"type": "default",
			"description": {
				"content": "",
				"type": "text/plain"
			},
			"enabled": true
		},
		{
			"key": "business_contact_number",
			"value": "",
			"type": "default",
			"description": {
				"content": "",
				"type": "text/plain"
			},
			"enabled": true
		},
		{
			"key": "address",
			"value": "",
			"type": "default",
			"description": {
				"content": "",
				"type": "text/plain"
			},
			"enabled": true
		},
		{
			"key": "business_license_id",
			"value": "",
			"type": "default",
			"description": {
				"content": "",
				"type": "text/plain"
			},
			"enabled": true
		},
		{
			"key": "compliance_document_url_1",
			"value": "",
			"type": "default",
			"description": {
				"content": "",
				"type": "text/plain"
			},
			"enabled": true
		},
		{
			"key": "compliance_document_url_2",
			"value": "",
			"type": "default",
			"description": {
				"content": "",
				"type": "text/plain"
			},
			"enabled": true
		},
		{
			"key": "approver1_email",
			"value": "finance@sapco.com",
			"type": "default",
			"description": {
				"content": "",
				"type": "text/plain"
			},
			"enabled": true
		},
		{
			"key": "approver2_email",
			"value": "legal@sapco.com",
			"type": "default",
			"description": {
				"content": "",
				"type": "text/plain"
			},
			"enabled": true
		},
		{
			"key": "approver3_email",
			"value": "procurement@sapco.com",
			"type": "default",
			"description": {
				"content": "",
				"type": "text/plain"
			},
			"enabled": true
		},
		{
			"key": "approver1_taskId",
			"value": "",
			"type": "any",
			"enabled": true
		},
		{
			"key": "approver2_taskId",
			"value": "",
			"type": "any",
			"enabled": true
		},
		{
			"key": "approver3_taskId",
			"value": "",
			"type": "any",
			"enabled": true
		}
	],
	"_postman_variable_scope": "environment",
	"_postman_exported_at": "2025-08-21T09:26:54.449Z",
	"_postman_exported_using": "Postman/11.59.3"
}